fount/__init__.py
fount-0.1.0.dist-info/METADATA
fount-0.1.0.dist-info/WHEEL
fount-0.1.0.dist-info/top_level.txt
fount-0.1.0.dist-info/RECORD
